typescript_routes/__init__.py
typescript_routes/lib/__init__.py
typescript_routes/lib/logic.py
typescript_routes/management/__init__.py
typescript_routes/management/commands/__init__.py
typescript_routes/management/commands/generate_typescript_routes.py
typescript_routes/templates/urls.ts.template
django_typescript_routes-0.3.0.dist-info/METADATA
django_typescript_routes-0.3.0.dist-info/WHEEL
django_typescript_routes-0.3.0.dist-info/licenses/LICENSE
django_typescript_routes-0.3.0.dist-info/RECORD
