Metadata-Version: 2.4
Name: django-typescript-routes
Version: 0.3.0
Summary: Generate typescript routes from a Django URLconf
Project-URL: Repository, https://github.com/buttondown-email/django-typescript-routes
Author-email: Justin Duke <justin@buttondown.email>
License-Expression: MIT
License-File: LICENSE
Requires-Python: ~=3.11
Requires-Dist: django<6,>=5
